cassiopeia/__init__.py
cassiopeia/cassiopeia.py
cassiopeia/data.py
cassiopeia/profile_icon_names.json
cassiopeia/_configuration/__init__.py
cassiopeia/_configuration/all_plugins.json
cassiopeia/_configuration/load.py
cassiopeia/_configuration/settings.py
cassiopeia/core/__init__.py
cassiopeia/core/account.py
cassiopeia/core/champion.py
cassiopeia/core/championmastery.py
cassiopeia/core/common.py
cassiopeia/core/league.py
cassiopeia/core/match.py
cassiopeia/core/patch.py
cassiopeia/core/spectator.py
cassiopeia/core/status.py
cassiopeia/core/summoner.py
cassiopeia/core/staticdata/__init__.py
cassiopeia/core/staticdata/champion.py
cassiopeia/core/staticdata/common.py
cassiopeia/core/staticdata/item.py
cassiopeia/core/staticdata/language.py
cassiopeia/core/staticdata/languagestrings.py
cassiopeia/core/staticdata/map.py
cassiopeia/core/staticdata/profileicon.py
cassiopeia/core/staticdata/realm.py
cassiopeia/core/staticdata/rune.py
cassiopeia/core/staticdata/summonerspell.py
cassiopeia/core/staticdata/version.py
cassiopeia/datastores/__init__.py
cassiopeia/datastores/cache.py
cassiopeia/datastores/common.py
cassiopeia/datastores/ddragon.py
cassiopeia/datastores/ghost.py
cassiopeia/datastores/image.py
cassiopeia/datastores/lolwikia.py
cassiopeia/datastores/merakianalyticscdn.py
cassiopeia/datastores/uniquekeys.py
cassiopeia/datastores/kernel/__init__.py
cassiopeia/datastores/kernel/account.py
cassiopeia/datastores/kernel/champion.py
cassiopeia/datastores/kernel/championmastery.py
cassiopeia/datastores/kernel/common.py
cassiopeia/datastores/kernel/leagues.py
cassiopeia/datastores/kernel/match.py
cassiopeia/datastores/kernel/spectator.py
cassiopeia/datastores/kernel/status.py
cassiopeia/datastores/kernel/summoner.py
cassiopeia/datastores/riotapi/__init__.py
cassiopeia/datastores/riotapi/account.py
cassiopeia/datastores/riotapi/champion.py
cassiopeia/datastores/riotapi/championmastery.py
cassiopeia/datastores/riotapi/common.py
cassiopeia/datastores/riotapi/leagues.py
cassiopeia-5.2.0.dist-info/LICENSE.txt
cassiopeia-5.2.0.dist-info/METADATA
cassiopeia-5.2.0.dist-info/WHEEL
cassiopeia-5.2.0.dist-info/top_level.txt
cassiopeia-5.2.0.dist-info/zip-safe
cassiopeia-5.2.0.dist-info/RECORD
