Metadata-Version: 2.2
Name: cassiopeia
Version: 5.2.0
Summary: Riot Games Developer API Wrapper (3rd Party)
Home-page: https://github.com/meraki-analytics/cassiopeia
Author: Jason Maldonis; Rob Rua
Author-email: Jason Maldonis <team@merakianalytics.com>, Rob Rua <team@merakianalytics.com>
License: MIT
Keywords: LoL,League of Legends,Riot Games,API,REST
Classifier: Development Status :: 4 - Beta
Classifier: Programming Language :: Python :: 3
Classifier: Environment :: Web Environment
Classifier: Operating System :: OS Independent
Classifier: Intended Audience :: Developers
Classifier: License :: OSI Approved :: MIT License
Classifier: Topic :: Games/Entertainment
Classifier: Topic :: Games/Entertainment :: Real Time Strategy
Classifier: Topic :: Games/Entertainment :: Role-Playing
Classifier: Topic :: Software Development :: Libraries :: Python Modules
Requires-Python: >=3.12
License-File: LICENSE.txt
Requires-Dist: flake8
Requires-Dist: pytest
Requires-Dist: merakicommons>=1.0.7
Requires-Dist: datapipelines>=1.0.7
Requires-Dist: Pillow
Requires-Dist: arrow
Requires-Dist: requests
Requires-Dist: dotenv>=0.9.9
Requires-Dist: matplotlib>=3.10.1
Requires-Dist: sortedcontainers>=2.4.0
Requires-Dist: setuptools>=76.0.0
Dynamic: author
Dynamic: home-page
Dynamic: requires-python
